fortunaisk/__init__.py
fortunaisk/admin.py
fortunaisk/apps.py
fortunaisk/auth_hooks.py
fortunaisk/decorators.py
fortunaisk/notifications.py
fortunaisk/tasks.py
fortunaisk/urls.py
fortunaisk/forms/__init__.py
fortunaisk/forms/autolottery_forms.py
fortunaisk/forms/lottery_forms.py
fortunaisk/management/commands/__init__.py
fortunaisk/management/commands/setup_fortuna_tasks.py
fortunaisk/migrations/0001_initial.py
fortunaisk/migrations/0002_general_alter_auditlog_options_and_more.py
fortunaisk/migrations/0003_ticketpurchase_quantity_alter_ticketpurchase_amount_and_more.py
fortunaisk/migrations/0004_consolidate_ticketpurchases.py
fortunaisk/migrations/0005_remove_ticketpurchase_unique_ticketpurchase_per_user_character.py
fortunaisk/migrations/0006_lowercase_interval_period.py
fortunaisk/migrations/0007_add_new_schema_squashed_0020_alter_ticketanomaly_detail.py
fortunaisk/migrations/0021_alter_autolottery_tax_alter_autolottery_tax_amount_and_more.py
fortunaisk/migrations/__init__.py
fortunaisk/models/__init__.py
fortunaisk/models/autolottery.py
fortunaisk/models/general.py
fortunaisk/models/lottery.py
fortunaisk/models/payment.py
fortunaisk/models/ticket.py
fortunaisk/models/webhook.py
fortunaisk/models/winner_distribution.py
fortunaisk/signals/__init__.py
fortunaisk/signals/autolottery_signals.py
fortunaisk/signals/lottery_signals.py
fortunaisk/signals/notifications_signals.py
fortunaisk/signals/webhook_signals.py
fortunaisk/static/css/.gitkeep
fortunaisk/static/css/clover.css
fortunaisk/static/css/styles.css
fortunaisk/static/js/clover.js
fortunaisk/static/js/loader.js
fortunaisk/static/js/sparkle.js
fortunaisk/templates/fortunaisk/admin.html
fortunaisk/templates/fortunaisk/anomalies_list.html
fortunaisk/templates/fortunaisk/auto_lottery_confirm_delete.html
fortunaisk/templates/fortunaisk/auto_lottery_form.html
fortunaisk/templates/fortunaisk/base.html
fortunaisk/templates/fortunaisk/distribute_prize_confirm.html
fortunaisk/templates/fortunaisk/lottery.html
fortunaisk-1.1.0.dist-info/licenses/LICENSE
fortunaisk-1.1.0.dist-info/WHEEL
fortunaisk-1.1.0.dist-info/METADATA
fortunaisk-1.1.0.dist-info/RECORD
