Metadata-Version: 2.4
Name: fortunaisk
Version: 1.1.0
Summary: fortunaisk Plugin for Alliance Auth
Keywords: allianceauth,eveonline,fortunaisk
Author-email: erka Ekanon <erkaekanon@outlook.com>
Requires-Python: >=3.8
Classifier: Environment :: Web Environment
Classifier: Framework :: Celery
Classifier: Framework :: Django
Classifier: Framework :: Django :: 4.0
Classifier: Framework :: Django :: 4.2
Classifier: Intended Audience :: Developers
Classifier: License :: OSI Approved :: MIT License
Classifier: Operating System :: OS Independent
Classifier: Programming Language :: Python
Classifier: Programming Language :: Python :: 3 :: Only
Classifier: Programming Language :: Python :: 3.8
Classifier: Programming Language :: Python :: 3.9
Classifier: Programming Language :: Python :: 3.10
Classifier: Programming Language :: Python :: 3.11
Classifier: Programming Language :: Python :: 3.12
Classifier: Programming Language :: Python :: 3.13
Classifier: Programming Language :: Python :: Implementation :: CPython
Classifier: Topic :: Internet :: WWW/HTTP
Classifier: Topic :: Internet :: WWW/HTTP :: Dynamic Content
License-File: LICENSE
Requires-Dist: aa-discordnotify>=2
Requires-Dist: allianceauth>=4,<5
Requires-Dist: allianceauth-corptools>=2.5.5
Project-URL: Home, https://github.com/Erkaek/aa-fortunaisk
Project-URL: Source, https://github.com/Erkaek/aa-fortunaisk
Project-URL: Tracker, https://github.com/Erkaek/aa-fortunaisk/issues
